todo_cmd/__init__.py
todo_cmd/language.json
todo_cmd/language.py
todo_cmd/main.py
todo_cmd/show.py
todo_cmd/templates.py
todo_cmd/validation.py
todo_cmd/interface/__init__.py
todo_cmd/interface/config.py
todo_cmd/interface/task.py
todo_cmd/interface/todo.py
todo_cmd/sub_cmd/__init__.py
todo_cmd/sub_cmd/init_todo.py
todo_cmd/sub_cmd/todo_add.py
todo_cmd/sub_cmd/todo_config.py
todo_cmd/sub_cmd/todo_discard.py
todo_cmd/sub_cmd/todo_done.py
todo_cmd/sub_cmd/todo_log.py
todo_cmd/sub_cmd/todo_ls.py
todo_cmd/sub_cmd/todo_mod.py
todo_cmd/sub_cmd/todo_rm.py
todo_cmd-1.0.1.dist-info/licenses/LICENSE
todo_cmd-1.0.1.dist-info/METADATA
todo_cmd-1.0.1.dist-info/WHEEL
todo_cmd-1.0.1.dist-info/entry_points.txt
todo_cmd-1.0.1.dist-info/top_level.txt
todo_cmd-1.0.1.dist-info/RECORD
