Metadata-Version: 2.4
Name: todo_cmd
Version: 1.0.1
Summary: A command line tool for managing todos.
Author: Tianyu Yuan
Author-email: Tianyu Yuan <1374736640@qq.com>
License: MIT
Requires-Python: >=3.7
License-File: LICENSE
Requires-Dist: click
Requires-Dist: rich
Requires-Dist: rich-click
Dynamic: author
Dynamic: license-file
